es2csv.py
es2csv_cli.py
es2csv-5.5.2.dist-info/DESCRIPTION.rst
es2csv-5.5.2.dist-info/entry_points.txt
es2csv-5.5.2.dist-info/METADATA
es2csv-5.5.2.dist-info/metadata.json
es2csv-5.5.2.dist-info/RECORD
es2csv-5.5.2.dist-info/top_level.txt
es2csv-5.5.2.dist-info/WHEEL
