Metadata-Version: 2.0
Name: es2csv
Version: 5.5.2
Summary: A CLI tool for exporting data from Elasticsearch into a CSV file.
Home-page: https://github.com/taraslayshchuk/es2csv
Author: Taras Layshchuk
Author-email: taraslayshchuk@gmail.com
License: Apache 2.0
Keywords: elasticsearch export kibana es bulk csv
Platform: UNKNOWN
Classifier: Development Status :: 5 - Production/Stable
Classifier: Intended Audience :: Developers
Classifier: Intended Audience :: System Administrators
Classifier: Environment :: Console
Classifier: License :: OSI Approved :: Apache Software License
Classifier: Programming Language :: Python :: 2 :: Only
Classifier: Programming Language :: Python :: 2.7
Classifier: Topic :: System :: Systems Administration
Classifier: Topic :: Database
Classifier: Topic :: Text Processing
Classifier: Topic :: Internet
Classifier: Topic :: Utilities
Requires-Python: ==2.7.*
Requires-Dist: elasticsearch (<5.6.0,>=5.5.2)
Requires-Dist: progressbar2 (<3.37.0,>=3.36.0)
Requires-Dist: backports.csv (<1.1.0,>=1.0.5)
